{
  "$schema": "https://schema.management.azure.com/schemas/2019-04-01/deploymentTemplate.json#",
  "contentVersion": "1.0.0.0",
  "parameters": {
    "applicationName": {
      "type": "string",
      "defaultValue": "[format('to-do-app{0}', uniqueString(resourceGroup().id))]"
    },
    "appServicePlanTier": {
      "type": "string"
    },
    "appServicePlanInstances": {
      "type": "int"
    },
    "webSiteName": {
      "type": "string"
    },
    "cosmosDb": {
      "type": "object"
    },
    "shouldDeployVm": {
      "type": "bool",
      "defaultValue": true
    }
  },
  "functions": [],
  "variables": {
    "hostingPlanName": "[parameters('applicationName')]",
    "location": "[resourceGroup().location]",
    "cosmosDbResourceId": "[resourceId('Microsoft.DocumentDB/databaseAccounts', parameters('cosmosDb').account)]",
    "_siteApiVersion": "2019-08-01",
    "_siteType": "Microsoft.Web/sites",
    "resourceCRef": {
      "id": "[resourceId('My.Rp/typeA/typeB', split(format('{0}/myName', 'resourceA'), '/')[0], split(format('{0}/myName', 'resourceA'), '/')[1])]"
    },
    "setResourceCRef": true,
    "myInterpKey": "abc",
    "storageAccounts": [
      {
        "name": "one",
        "location": "eastus2"
      },
      {
        "name": "two",
        "location": "westus"
      }
    ],
    "canHaveDuplicatesAcrossScopes": "hello",
    "duplicatesEverywhere": "hello"
  },
  "resources": [
    {
      "type": "Microsoft.Storage/storageAccounts",
      "apiVersion": "2019-06-01",
      "name": "basicblobs",
      "location": "westus",
      "kind": "BlobStorage",
      "sku": {
        "name": "Standard_GRS"
      }
    },
    {
      "type": "Microsoft.Network/dnszones",
      "apiVersion": "2018-05-01",
      "name": "myZone",
      "location": "global"
    },
    {
      "type": "Microsoft.Storage/storageAccounts",
      "apiVersion": "2017-10-01",
      "name": "myencryptedone",
      "location": "eastus2",
      "properties": {
        "supportsHttpsTrafficOnly": true,
        "accessTier": "Hot",
        "encryption": {
          "keySource": "Microsoft.Storage",
          "services": {
            "blob": {
              "enabled": true
            },
            "file": {
              "enabled": true
            }
          }
        }
      },
      "kind": "StorageV2",
      "sku": {
        "name": "Standard_LRS"
      }
    },
    {
      "type": "Microsoft.Storage/storageAccounts",
      "apiVersion": "2017-10-01",
      "name": "myencryptedone2",
      "location": "eastus2",
      "properties": {
        "supportsHttpsTrafficOnly": "[not(false())]",
        "accessTier": "[if(true(), 'Hot', 'Cold')]",
        "encryption": {
          "keySource": "Microsoft.Storage",
          "services": {
            "blob": {
              "enabled": "[or(true(), false())]"
            },
            "file": {
              "enabled": true
            }
          }
        }
      },
      "kind": "StorageV2",
      "sku": {
        "name": "Standard_LRS"
      },
      "dependsOn": [
        "[resourceId('Microsoft.Storage/storageAccounts', 'myencryptedone')]"
      ]
    },
    {
      "type": "Microsoft.Web/serverFarms",
      "apiVersion": "2019-08-01",
      "name": "[variables('hostingPlanName')]",
      "location": "[variables('location')]",
      "sku": {
        "name": "[parameters('appServicePlanTier')]",
        "capacity": "[parameters('appServicePlanInstances')]"
      },
      "properties": {
        "name": "[variables('hostingPlanName')]"
      }
    },
    {
      "type": "Microsoft.Web/sites",
      "apiVersion": "2019-08-01",
      "name": "[parameters('webSiteName')]",
      "location": "[variables('location')]",
      "properties": {
        "siteConfig": {
          "appSettings": [
            {
              "name": "CosmosDb:Account",
              "value": "[reference(variables('cosmosDbResourceId')).documentEndpoint]"
            },
            {
              "name": "CosmosDb:Key",
              "value": "[listKeys(variables('cosmosDbResourceId'), '2020-04-01').primaryMasterKey]"
            },
            {
              "name": "CosmosDb:DatabaseName",
              "value": "[parameters('cosmosDb').databaseName]"
            },
            {
              "name": "CosmosDb:ContainerName",
              "value": "[parameters('cosmosDb').containerName]"
            }
          ]
        }
      }
    },
    {
      "type": "Microsoft.Resources/deployments",
      "apiVersion": "2019-10-01",
      "name": "nestedTemplate1",
      "properties": {
        "mode": "Incremental",
        "template": {
          "$schema": "https://schema.management.azure.com/schemas/2019-04-01/deploymentTemplate.json#",
          "contentVersion": "1.0.0.0",
          "resources": []
        }
      }
    },
    {
      "type": "Microsoft.Foo/foos",
      "apiVersion": "2019-10-01",
      "name": "nestedTemplate1",
      "properties": {
        "otherId": "[resourceId('Microsoft.Resources/deployments', 'nestedTemplate1')]",
        "otherName": "nestedTemplate1",
        "otherVersion": "2019-10-01",
        "otherType": "Microsoft.Resources/deployments",
        "otherThings": "[reference(resourceId('Microsoft.Resources/deployments', 'nestedTemplate1')).mode]"
      },
      "dependsOn": [
        "[resourceId('Microsoft.Resources/deployments', 'nestedTemplate1')]"
      ]
    },
    {
      "type": "My.Rp/typeA",
      "apiVersion": "2020-01-01",
      "name": "resourceA"
    },
    {
      "type": "My.Rp/typeA/typeB",
      "apiVersion": "2020-01-01",
      "name": "[format('{0}/myName', 'resourceA')]",
      "dependsOn": [
        "[resourceId('My.Rp/typeA', 'resourceA')]"
      ]
    },
    {
      "type": "My.Rp/typeA/typeB",
      "apiVersion": "2020-01-01",
      "name": "[format('{0}/myName', 'resourceA')]",
      "properties": {
        "aId": "[resourceId('My.Rp/typeA', 'resourceA')]",
        "aType": "My.Rp/typeA",
        "aName": "resourceA",
        "aApiVersion": "2020-01-01",
        "bProperties": "[reference(resourceId('My.Rp/typeA/typeB', split(format('{0}/myName', 'resourceA'), '/')[0], split(format('{0}/myName', 'resourceA'), '/')[1]))]"
      },
      "dependsOn": [
        "[resourceId('My.Rp/typeA', 'resourceA')]",
        "[resourceId('My.Rp/typeA/typeB', split(format('{0}/myName', 'resourceA'), '/')[0], split(format('{0}/myName', 'resourceA'), '/')[1])]"
      ]
    },
    {
      "type": "My.Rp/typeD",
      "apiVersion": "2020-01-01",
      "name": "constant",
      "properties": {
        "runtime": [
          {
            "bId": "[resourceId('My.Rp/typeA/typeB', split(format('{0}/myName', 'resourceA'), '/')[0], split(format('{0}/myName', 'resourceA'), '/')[1])]",
            "bType": "My.Rp/typeA/typeB",
            "bName": "[format('{0}/myName', 'resourceA')]",
            "bApiVersion": "2020-01-01",
            "aKind": "[reference(resourceId('My.Rp/typeA', 'resourceA'), '2020-01-01', 'full').kind]"
          }
        ],
        "repro316": "[if(variables('setResourceCRef'), variables('resourceCRef'), null())]"
      },
      "dependsOn": [
        "[resourceId('My.Rp/typeA', 'resourceA')]",
        "[resourceId('My.Rp/typeA/typeB', split(format('{0}/myName', 'resourceA'), '/')[0], split(format('{0}/myName', 'resourceA'), '/')[1])]",
        "[resourceId('My.Rp/typeA/typeB', split(format('{0}/myName', 'resourceA'), '/')[0], split(format('{0}/myName', 'resourceA'), '/')[1])]"
      ]
    },
    {
      "type": "My.Rp/interp",
      "apiVersion": "2020-01-01",
      "name": "interpTest",
      "properties": {
        "[variables('myInterpKey')]": 1,
        "[format('abc{0}def', variables('myInterpKey'))]": 2,
        "[format('{0}abc{1}', variables('myInterpKey'), variables('myInterpKey'))]": 3
      }
    },
    {
      "type": "My.Rp/mockResource",
      "apiVersion": "2020-01-01",
      "name": "test",
      "properties": {
        "[[resourceGroup().location]": "[[resourceGroup().location]"
      }
    },
    {
      "condition": "[parameters('shouldDeployVm')]",
      "type": "Microsoft.Compute/virtualMachines",
      "apiVersion": "2020-06-01",
      "name": "vmName",
      "location": "westus",
      "properties": {
        "osProfile": {
          "windowsConfiguration": {
            "enableAutomaticUpdates": true
          }
        }
      }
    },
    {
      "type": "My.Rp/extensionResource",
      "apiVersion": "2020-12-01",
      "scope": "[format('Microsoft.Compute/virtualMachines/{0}', 'vmName')]",
      "name": "extension",
      "dependsOn": [
        "[resourceId('Microsoft.Compute/virtualMachines', 'vmName')]"
      ]
    },
    {
      "type": "My.Rp/extensionResource",
      "apiVersion": "2020-12-01",
      "scope": "[extensionResourceId(format('Microsoft.Compute/virtualMachines/{0}', 'vmName'), 'My.Rp/extensionResource', 'extension')]",
      "name": "extension",
      "dependsOn": [
        "[extensionResourceId(resourceId('Microsoft.Compute/virtualMachines', 'vmName'), 'My.Rp/extensionResource', 'extension')]"
      ]
    },
    {
      "type": "My.Rp/mockResource",
      "apiVersion": "2020-01-01",
      "name": "extensionDependencies",
      "properties": {
        "res1": "[resourceId('Microsoft.Compute/virtualMachines', 'vmName')]",
        "res1runtime": "[reference(resourceId('Microsoft.Compute/virtualMachines', 'vmName')).something]",
        "res2": "[extensionResourceId(resourceId('Microsoft.Compute/virtualMachines', 'vmName'), 'My.Rp/extensionResource', 'extension')]",
        "res2runtime": "[reference(extensionResourceId(resourceId('Microsoft.Compute/virtualMachines', 'vmName'), 'My.Rp/extensionResource', 'extension')).something]",
        "res3": "[extensionResourceId(extensionResourceId(resourceId('Microsoft.Compute/virtualMachines', 'vmName'), 'My.Rp/extensionResource', 'extension'), 'My.Rp/extensionResource', 'extension')]",
        "res3runtime": "[reference(extensionResourceId(extensionResourceId(resourceId('Microsoft.Compute/virtualMachines', 'vmName'), 'My.Rp/extensionResource', 'extension'), 'My.Rp/extensionResource', 'extension')).something]"
      },
      "dependsOn": [
        "[extensionResourceId(resourceId('Microsoft.Compute/virtualMachines', 'vmName'), 'My.Rp/extensionResource', 'extension')]",
        "[extensionResourceId(extensionResourceId(resourceId('Microsoft.Compute/virtualMachines', 'vmName'), 'My.Rp/extensionResource', 'extension'), 'My.Rp/extensionResource', 'extension')]",
        "[resourceId('Microsoft.Compute/virtualMachines', 'vmName')]"
      ]
    },
    {
      "type": "My.Rp/extensionResource",
      "apiVersion": "2020-12-01",
      "scope": "[extensionResourceId(extensionResourceId(format('Microsoft.Compute/virtualMachines/{0}', 'vmName'), 'My.Rp/extensionResource', 'extension'), 'Mock.Rp/existingExtensionResource', 'existing1')]",
      "name": "extension3",
      "dependsOn": []
    },
    {
      "copy": {
        "name": "storageResources",
        "count": "[length(variables('storageAccounts'))]"
      },
      "type": "Microsoft.Storage/storageAccounts",
      "apiVersion": "2019-06-01",
      "name": "[variables('storageAccounts')[copyIndex()].name]",
      "location": "[variables('storageAccounts')[copyIndex()].location]",
      "sku": {
        "name": "Standard_LRS"
      },
      "kind": "StorageV2"
    },
    {
      "copy": {
        "name": "storageResourcesWithIndex",
        "count": "[length(variables('storageAccounts'))]"
      },
      "type": "Microsoft.Storage/storageAccounts",
      "apiVersion": "2019-06-01",
      "name": "[format('{0}{1}', variables('storageAccounts')[copyIndex()].name, copyIndex())]",
      "location": "[variables('storageAccounts')[copyIndex()].location]",
      "sku": {
        "name": "Standard_LRS"
      },
      "kind": "StorageV2"
    },
    {
      "copy": {
        "name": "vnet",
        "count": "[length(range(0, 3))]"
      },
      "type": "Microsoft.Network/virtualNetworks",
      "apiVersion": "2020-06-01",
      "name": "[format('vnet-{0}', range(0, 3)[copyIndex()])]",
      "properties": {
        "copy": [
          {
            "name": "subnets",
            "count": "[length(range(0, 4))]",
            "input": {
              "name": "[format('subnet-{0}-{1}', range(0, 3)[copyIndex()], range(0, 4)[copyIndex('subnets')])]"
            }
          }
        ]
      }
    },
    {
      "copy": {
        "name": "duplicateIdentifiersWithinLoop",
        "count": "[length(range(0, 3))]"
      },
      "type": "Microsoft.Network/virtualNetworks",
      "apiVersion": "2020-06-01",
      "name": "[format('vnet-{0}', range(0, 3)[copyIndex()])]",
      "properties": {
        "copy": [
          {
            "name": "subnets",
            "count": "[length(range(0, 4))]",
            "input": {
              "name": "[format('subnet-{0}-{1}', range(0, 4)[copyIndex('subnets')], range(0, 4)[copyIndex('subnets')])]"
            }
          }
        ]
      }
    },
    {
      "copy": {
        "name": "duplicateInGlobalAndOneLoop",
        "count": "[length(range(0, 3))]"
      },
      "type": "Microsoft.Network/virtualNetworks",
      "apiVersion": "2020-06-01",
      "name": "[format('vnet-{0}', range(0, 3)[copyIndex()])]",
      "properties": {
        "copy": [
          {
            "name": "subnets",
            "count": "[length(range(0, 4))]",
            "input": {
              "name": "[format('subnet-{0}-{1}', range(0, 4)[copyIndex('subnets')], range(0, 4)[copyIndex('subnets')])]"
            }
          }
        ]
      }
    },
    {
      "copy": {
        "name": "duplicateInGlobalAndTwoLoops",
        "count": "[length(range(0, 3))]"
      },
      "type": "Microsoft.Network/virtualNetworks",
      "apiVersion": "2020-06-01",
      "name": "[format('vnet-{0}', range(0, 3)[copyIndex()])]",
      "properties": {
        "copy": [
          {
            "name": "subnets",
            "count": "[length(range(0, 4))]",
            "input": {
              "name": "[format('subnet-{0}', range(0, 4)[copyIndex('subnets')])]"
            }
          }
        ]
      }
    }
  ],
  "outputs": {
    "siteApiVersion": {
      "type": "string",
      "value": "2019-08-01"
    },
    "siteType": {
      "type": "string",
      "value": "Microsoft.Web/sites"
    }
  },
  "metadata": {
    "_generator": {
      "name": "bicep",
      "version": "dev",
      "templateHash": "5587874887754515167"
    }
  }
}